{
  "call_id": "iemocap_Ses01M_impro06_M021",
  "agent_id": "iemocap_agent_01_M",
  "timestamp": "2025-12-21T01:58:46.707582",
  "duration_seconds": 2.13,
  "transcript": "There.",
  "segments": [
    {
      "start_time": 0.0,
      "end_time": 2.0,
      "text": "There.",
      "emotion": "neutral",
      "emotion_confidence": 0.896,
      "sentiment_score": 0.2056,
      "pitch_mean": 327.69
    }
  ],
  "overall_metrics": {
    "avg_sentiment": 0.2056,
    "dominant_emotion": "neutral",
    "emotion_distribution": {
      "neutral": 1.0
    },
    "escalation_flag": false,
    "agent_stress_score": 0.2,
    "speech_rate_wpm": 28.17,
    "avg_pitch": 328.66
  },
  "ground_truth": {
    "emotion": "sadness",
    "raw_emotion": "sad",
    "valence": 2.0,
    "arousal": 2.0,
    "dominance": 3.5
  },
  "metadata": {
    "dataset": "IEMOCAP",
    "session": 1,
    "dialogue": "Ses01M_impro06",
    "utterance_id": "Ses01M_impro06_M021",
    "transcript_ground_truth": "Yeah."
  }
}