{
  "call_id": "iemocap_Ses02M_impro03_F020",
  "agent_id": "iemocap_agent_02_M",
  "timestamp": "2025-12-21T02:49:52.695657",
  "duration_seconds": 2.58,
  "transcript": "Oh, that would be fine.",
  "segments": [
    {
      "start_time": 0.0,
      "end_time": 2.0,
      "text": "Oh, that would be fine.",
      "emotion": "neutral",
      "emotion_confidence": 0.578,
      "sentiment_score": 0.8531,
      "pitch_mean": 359.39
    }
  ],
  "overall_metrics": {
    "avg_sentiment": 0.8531,
    "dominant_emotion": "neutral",
    "emotion_distribution": {
      "neutral": 1.0
    },
    "escalation_flag": false,
    "agent_stress_score": 0.2,
    "speech_rate_wpm": 116.28,
    "avg_pitch": 355.8
  },
  "ground_truth": {
    "emotion": "joy",
    "raw_emotion": "exc",
    "valence": 4.0,
    "arousal": 3.5,
    "dominance": 3.5
  },
  "metadata": {
    "dataset": "IEMOCAP",
    "session": 2,
    "dialogue": "Ses02M_impro03",
    "utterance_id": "Ses02M_impro03_F020",
    "transcript_ground_truth": "Ooh, that would be fun."
  }
}