{
  "call_id": "iemocap_Ses03M_impro05b_M005",
  "agent_id": "iemocap_agent_03_M",
  "timestamp": "2025-12-21T03:59:52.008575",
  "duration_seconds": 2.91,
  "transcript": "Now what are you gonna do for me different?",
  "segments": [
    {
      "start_time": 0.0,
      "end_time": 2.0,
      "text": "Now what are you gonna do for me different?",
      "emotion": "disgust",
      "emotion_confidence": 0.327,
      "sentiment_score": -0.029,
      "pitch_mean": 311.64
    }
  ],
  "overall_metrics": {
    "avg_sentiment": -0.029,
    "dominant_emotion": "disgust",
    "emotion_distribution": {
      "disgust": 1.0
    },
    "escalation_flag": false,
    "agent_stress_score": 0.5,
    "speech_rate_wpm": 185.57,
    "avg_pitch": 317.96
  },
  "ground_truth": {
    "emotion": "anger",
    "raw_emotion": "fru",
    "valence": 2.5,
    "arousal": 2.0,
    "dominance": 4.0
  },
  "metadata": {
    "dataset": "IEMOCAP",
    "session": 3,
    "dialogue": "Ses03M_impro05b",
    "utterance_id": "Ses03M_impro05b_M005",
    "transcript_ground_truth": "Now what are you going to do for me different? Hmm?"
  }
}