{
  "call_id": "iemocap_Ses01F_impro04_F015",
  "agent_id": "iemocap_agent_01_M",
  "timestamp": "2025-12-21T01:21:36.974252",
  "duration_seconds": 6.11,
  "transcript": "I don't like sending things in the mail. I don't want my information out there.",
  "segments": [
    {
      "start_time": 0.0,
      "end_time": 6.0,
      "text": "I don't like sending things in the mail. I don't want my information out there.",
      "emotion": "disgust",
      "emotion_confidence": 0.772,
      "sentiment_score": -0.8291,
      "pitch_mean": 352.66
    }
  ],
  "overall_metrics": {
    "avg_sentiment": -0.8291,
    "dominant_emotion": "disgust",
    "emotion_distribution": {
      "disgust": 1.0
    },
    "escalation_flag": true,
    "agent_stress_score": 0.2,
    "speech_rate_wpm": 147.31,
    "avg_pitch": 353.02
  },
  "ground_truth": {
    "emotion": "neutral",
    "raw_emotion": "xxx",
    "valence": 2.0,
    "arousal": 4.0,
    "dominance": 3.5
  },
  "metadata": {
    "dataset": "IEMOCAP",
    "session": 1,
    "dialogue": "Ses01F_impro04",
    "utterance_id": "Ses01F_impro04_F015",
    "transcript_ground_truth": "I don't like- I don't like sending things in the mail.  I don't want my information out there."
  }
}