{
  "call_id": "iemocap_Ses02M_impro08_M010",
  "agent_id": "iemocap_agent_02_M",
  "timestamp": "2025-12-21T02:58:49.367942",
  "duration_seconds": 1.9,
  "transcript": "It'll work out fine.",
  "segments": [
    {
      "start_time": 0.0,
      "end_time": 2.0,
      "text": "It'll work out fine.",
      "emotion": "neutral",
      "emotion_confidence": 0.897,
      "sentiment_score": 0.6501,
      "pitch_mean": 340.41
    }
  ],
  "overall_metrics": {
    "avg_sentiment": 0.6501,
    "dominant_emotion": "neutral",
    "emotion_distribution": {
      "neutral": 1.0
    },
    "escalation_flag": false,
    "agent_stress_score": 0.2,
    "speech_rate_wpm": 126.19,
    "avg_pitch": 340.41
  },
  "ground_truth": {
    "emotion": "neutral",
    "raw_emotion": "neu",
    "valence": 3.0,
    "arousal": 3.0,
    "dominance": 3.0
  },
  "metadata": {
    "dataset": "IEMOCAP",
    "session": 2,
    "dialogue": "Ses02M_impro08",
    "utterance_id": "Ses02M_impro08_M010",
    "transcript_ground_truth": "it- it'll work out fine."
  }
}