{
  "call_id": "iemocap_Ses01F_script02_2_F038",
  "agent_id": "iemocap_agent_01_M",
  "timestamp": "2025-12-21T01:41:09.939442",
  "duration_seconds": 3.45,
  "transcript": "Yeah, don't you know that?",
  "segments": [
    {
      "start_time": 0.0,
      "end_time": 3.0,
      "text": "Yeah, don't you know that?",
      "emotion": "disgust",
      "emotion_confidence": 0.467,
      "sentiment_score": -0.2962,
      "pitch_mean": 337.61
    }
  ],
  "overall_metrics": {
    "avg_sentiment": -0.2962,
    "dominant_emotion": "disgust",
    "emotion_distribution": {
      "disgust": 1.0
    },
    "escalation_flag": false,
    "agent_stress_score": 0.2,
    "speech_rate_wpm": 86.96,
    "avg_pitch": 336.52
  },
  "ground_truth": {
    "emotion": "neutral",
    "raw_emotion": "sur",
    "valence": 2.5,
    "arousal": 3.5,
    "dominance": 2.5
  },
  "metadata": {
    "dataset": "IEMOCAP",
    "session": 1,
    "dialogue": "Ses01F_script02_2",
    "utterance_id": "Ses01F_script02_2_F038",
    "transcript_ground_truth": "Yeah.  Don't you know that?"
  }
}