{
  "call_id": "iemocap_Ses02M_script01_1_M037",
  "agent_id": "iemocap_agent_02_M",
  "timestamp": "2025-12-21T03:02:03.713199",
  "duration_seconds": 4.35,
  "transcript": "I've been a good son too long, a good sucker. I'm through with it.",
  "segments": [
    {
      "start_time": 0.0,
      "end_time": 4.0,
      "text": "I've been a good son too long, a good sucker. I'm through with it.",
      "emotion": "disgust",
      "emotion_confidence": 0.384,
      "sentiment_score": -0.8567,
      "pitch_mean": 325.12
    }
  ],
  "overall_metrics": {
    "avg_sentiment": -0.8567,
    "dominant_emotion": "disgust",
    "emotion_distribution": {
      "disgust": 1.0
    },
    "escalation_flag": true,
    "agent_stress_score": 0.5,
    "speech_rate_wpm": 193.11,
    "avg_pitch": 322.51
  },
  "ground_truth": {
    "emotion": "anger",
    "raw_emotion": "ang",
    "valence": 1.5,
    "arousal": 3.5,
    "dominance": 4.5
  },
  "metadata": {
    "dataset": "IEMOCAP",
    "session": 2,
    "dialogue": "Ses02M_script01_1",
    "utterance_id": "Ses02M_script01_1_M037",
    "transcript_ground_truth": "I've been a good son too long a good sucker, I'm through with it."
  }
}