{
  "call_id": "iemocap_Ses02F_impro07_M025",
  "agent_id": "iemocap_agent_02_M",
  "timestamp": "2025-12-21T02:29:36.009696",
  "duration_seconds": 0.91,
  "transcript": "out as well.",
  "segments": [
    {
      "start_time": 0.0,
      "end_time": 1.0,
      "text": "out as well.",
      "emotion": "neutral",
      "emotion_confidence": 0.629,
      "sentiment_score": 0.019,
      "pitch_mean": 365.0
    }
  ],
  "overall_metrics": {
    "avg_sentiment": 0.019,
    "dominant_emotion": "neutral",
    "emotion_distribution": {
      "neutral": 1.0
    },
    "escalation_flag": false,
    "agent_stress_score": 0.5,
    "speech_rate_wpm": 198.36,
    "avg_pitch": 365.0
  },
  "ground_truth": {
    "emotion": "neutral",
    "raw_emotion": "xxx",
    "valence": 4.0,
    "arousal": 3.0,
    "dominance": 3.0
  },
  "metadata": {
    "dataset": "IEMOCAP",
    "session": 2,
    "dialogue": "Ses02F_impro07",
    "utterance_id": "Ses02F_impro07_M025",
    "transcript_ground_truth": "You know is like."
  }
}