{
  "call_id": "iemocap_Ses05F_impro03_M047",
  "agent_id": "iemocap_agent_05_M",
  "timestamp": "2025-12-21T14:54:59.951731",
  "duration_seconds": 1.65,
  "transcript": "Who left me tall?",
  "segments": [
    {
      "start_time": 0.0,
      "end_time": 2.0,
      "text": "Who left me tall?",
      "emotion": "neutral",
      "emotion_confidence": 0.599,
      "sentiment_score": -0.2085,
      "pitch_mean": 324.17
    }
  ],
  "overall_metrics": {
    "avg_sentiment": -0.2085,
    "dominant_emotion": "neutral",
    "emotion_distribution": {
      "neutral": 1.0
    },
    "escalation_flag": false,
    "agent_stress_score": 0.2,
    "speech_rate_wpm": 145.46,
    "avg_pitch": 324.17
  },
  "ground_truth": {
    "emotion": "neutral",
    "raw_emotion": "xxx",
    "valence": 3.5,
    "arousal": 2.5,
    "dominance": 3.0
  },
  "metadata": {
    "dataset": "IEMOCAP",
    "session": 5,
    "dialogue": "Ses05F_impro03",
    "utterance_id": "Ses05F_impro03_M047",
    "transcript_ground_truth": "Who else have you told?"
  }
}