{
  "call_id": "iemocap_Ses02M_script03_2_M032",
  "agent_id": "iemocap_agent_02_M",
  "timestamp": "2025-12-21T03:14:48.822151",
  "duration_seconds": 2.64,
  "transcript": "Alright, I will.",
  "segments": [
    {
      "start_time": 0.0,
      "end_time": 2.0,
      "text": "Alright, I will.",
      "emotion": "neutral",
      "emotion_confidence": 0.711,
      "sentiment_score": 0.3944,
      "pitch_mean": 332.82
    }
  ],
  "overall_metrics": {
    "avg_sentiment": 0.3944,
    "dominant_emotion": "neutral",
    "emotion_distribution": {
      "neutral": 1.0
    },
    "escalation_flag": false,
    "agent_stress_score": 0.2,
    "speech_rate_wpm": 68.15,
    "avg_pitch": 328.79
  },
  "ground_truth": {
    "emotion": "neutral",
    "raw_emotion": "neu",
    "valence": 3.5,
    "arousal": 3.0,
    "dominance": 3.5
  },
  "metadata": {
    "dataset": "IEMOCAP",
    "session": 2,
    "dialogue": "Ses02M_script03_2",
    "utterance_id": "Ses02M_script03_2_M032",
    "transcript_ground_truth": "All right. I will."
  }
}