{
  "call_id": "iemocap_Ses05M_script01_2_F009",
  "agent_id": "iemocap_agent_05_M",
  "timestamp": "2025-12-21T15:59:48.448393",
  "duration_seconds": 8.35,
  "transcript": "Nobody in this house dares take her fate the way Joe. Strangers might, but not his father, not his brother.",
  "segments": [
    {
      "start_time": 0.0,
      "end_time": 4.0,
      "text": "Nobody in this house dares take her fate the way Joe.",
      "emotion": "disgust",
      "emotion_confidence": 0.413,
      "sentiment_score": -0.8627,
      "pitch_mean": 320.84
    },
    {
      "start_time": 4.0,
      "end_time": 8.0,
      "text": "Strangers might, but not his father, not his brother.",
      "emotion": "neutral",
      "emotion_confidence": 0.841,
      "sentiment_score": -0.2262,
      "pitch_mean": 329.38
    }
  ],
  "overall_metrics": {
    "avg_sentiment": -0.5445,
    "dominant_emotion": "disgust",
    "emotion_distribution": {
      "disgust": 0.5,
      "neutral": 0.5
    },
    "escalation_flag": true,
    "agent_stress_score": 0.2,
    "speech_rate_wpm": 143.71,
    "avg_pitch": 324.84
  },
  "ground_truth": {
    "emotion": "neutral",
    "raw_emotion": "xxx",
    "valence": 2.3333,
    "arousal": 3.3333,
    "dominance": 3.6667
  },
  "metadata": {
    "dataset": "IEMOCAP",
    "session": 5,
    "dialogue": "Ses05M_script01_2",
    "utterance_id": "Ses05M_script01_2_F009",
    "transcript_ground_truth": "Nobody in this house dares takes her faith away, Joe.  Strangers might, but not his father, not his brother."
  }
}