{
  "call_id": "iemocap_Ses05M_script03_2_M015",
  "agent_id": "iemocap_agent_05_M",
  "timestamp": "2025-12-21T16:15:04.378169",
  "duration_seconds": 2.0,
  "transcript": "I made a really...",
  "segments": [
    {
      "start_time": 0.0,
      "end_time": 2.0,
      "text": "I made a really...",
      "emotion": "joy",
      "emotion_confidence": 0.684,
      "sentiment_score": 0.0554,
      "pitch_mean": 316.46
    }
  ],
  "overall_metrics": {
    "avg_sentiment": 0.0554,
    "dominant_emotion": "joy",
    "emotion_distribution": {
      "joy": 1.0
    },
    "escalation_flag": false,
    "agent_stress_score": 0.2,
    "speech_rate_wpm": 120.0,
    "avg_pitch": 316.46
  },
  "ground_truth": {
    "emotion": "anger",
    "raw_emotion": "ang",
    "valence": 1.5,
    "arousal": 3.0,
    "dominance": 3.5
  },
  "metadata": {
    "dataset": "IEMOCAP",
    "session": 5,
    "dialogue": "Ses05M_script03_2",
    "utterance_id": "Ses05M_script03_2_M015",
    "transcript_ground_truth": "Amanda, really."
  }
}